flowweave/__init__.py
flowweave/base.py
flowweave/cli.py
flowweave/flowweave.py
flowweave/message.py
flowweave/schema/flow.json
flowweave/schema/op_code.json
flowweave-1.0.1.dist-info/licenses/LICENSE
flowweave-1.0.1.dist-info/METADATA
flowweave-1.0.1.dist-info/WHEEL
flowweave-1.0.1.dist-info/entry_points.txt
flowweave-1.0.1.dist-info/top_level.txt
flowweave-1.0.1.dist-info/RECORD
