Metadata-Version: 2.4
Name: flowweave
Version: 1.0.1
Summary: YAML-based workflow runner for task orchestration
Author: syatch
License: MIT
Requires-Python: >=3.9
License-File: LICENSE
Requires-Dist: colorama>=0.4.6
Requires-Dist: jsonschema>=4.25.0
Requires-Dist: prefect<3,>=2
Requires-Dist: pyyaml<7,>=6
Dynamic: license-file
